{
    "org.apache.commons.cli2$DisplaySetting": 0.0,
    "org.apache.commons.cli2$OptionException": 0.0,
    "org.apache.commons.cli2.builder$ArgumentBuilder": 0.0,
    "org.apache.commons.cli2.builder$CommandBuilder": 0.0,
    "org.apache.commons.cli2.builder$DefaultOptionBuilder": 0.0,
    "org.apache.commons.cli2.builder$GroupBuilder": 0.10867853340033277,
    "org.apache.commons.cli2.builder$PatternBuilder": 0,
    "org.apache.commons.cli2.builder$SwitchBuilder": 0.0,
    "org.apache.commons.cli2.commandline$CommandLineImpl": 0.0,
    "org.apache.commons.cli2.commandline$DefaultingCommandLine": 0.0,
    "org.apache.commons.cli2.commandline$Parser": 0.5773502691896258,
    "org.apache.commons.cli2.commandline$PreferencesCommandLine": 0.0,
    "org.apache.commons.cli2.commandline$PropertiesCommandLine": 0.0,
    "org.apache.commons.cli2.commandline$WriteableCommandLineImpl": 0.0,
    "org.apache.commons.cli2.option$ArgumentImpl": 0.2526455763199557,
    "org.apache.commons.cli2.option$Command": 0.0,
    "org.apache.commons.cli2.option$DefaultOption": 0.10406884697039405,
    "org.apache.commons.cli2.option$GroupImpl": 0.23791547571544325,
    "org.apache.commons.cli2.option$HelpLineImpl": 0.0,
    "org.apache.commons.cli2.option$OptionImpl": 0,
    "org.apache.commons.cli2.option$ParentImpl": 0.24494897427831783,
    "org.apache.commons.cli2.option$PropertyOption": 0.0,
    "org.apache.commons.cli2.option$ReverseStringComparator": 0.10502100630210073,
    "org.apache.commons.cli2.option$SourceDestArgument": 0.0,
    "org.apache.commons.cli2.option$Switch": 0.0,
    "org.apache.commons.cli2.resource$ResourceHelper": 0.054312544659356844,
    "org.apache.commons.cli2.util$Comparators": 0.0,
    "org.apache.commons.cli2.util$Comparators$Chain": 0.0,
    "org.apache.commons.cli2.util$Comparators$CommandFirst": 0,
    "org.apache.commons.cli2.util$Comparators$DefaultOptionFirst": 0,
    "org.apache.commons.cli2.util$Comparators$GroupFirst": 0,
    "org.apache.commons.cli2.util$Comparators$Named": 0.0,
    "org.apache.commons.cli2.util$Comparators$PreferredName": 0.0,
    "org.apache.commons.cli2.util$Comparators$Required": 0,
    "org.apache.commons.cli2.util$Comparators$Reverse": 0.0,
    "org.apache.commons.cli2.util$Comparators$SwitchFirst": 0,
    "org.apache.commons.cli2.util$HelpFormatter": 0.0,
    "org.apache.commons.cli2.validation$ClassValidator": 0.0,
    "org.apache.commons.cli2.validation$DateValidator": 0.0,
    "org.apache.commons.cli2.validation$EnumValidator": 0.0,
    "org.apache.commons.cli2.validation$FileValidator": 0.0,
    "org.apache.commons.cli2.validation$InvalidArgumentException": 0.0,
    "org.apache.commons.cli2.validation$NumberValidator": 0.0,
    "org.apache.commons.cli2.validation$UrlValidator": 0.0
}